<?xml version="1.0" encoding="UTF-8"?>
<objects serializationModel="Studio.02.01.00">
	<object class="AudioFile" id="{89ae0a4f-537e-4343-a2ec-2f2112c7260c}">
		<property name="assetPath">
			<value>Piano Key 48-Audio.wav</value>
		</property>
		<property name="isStreaming">
			<value>true</value>
		</property>
		<property name="frequencyInKHz">
			<value>48</value>
		</property>
		<property name="channelCount">
			<value>2</value>
		</property>
		<property name="length">
			<value>1.7142916666666668</value>
		</property>
		<relationship name="masterAssetFolder">
			<destination>{931b03c8-522a-4587-b118-8c45c5b720aa}</destination>
		</relationship>
	</object>
</objects>
